[
  {
    "icon_name": "sliders",
    "is_active": true,
    "is_system_defined": true,
    "module_code": "MOD-SETTINGS",
    "module_description": "Configuration, controls, integrations, and user preferences",
    "module_name": "Settings",
    "route_base": "/settings",
    "sort_order": 60,
    "id": "69c08ed5f687124ea429fe13",
    "created_date": "2026-03-23T00:52:37.535000",
    "updated_date": "2026-03-23T00:52:37.535000",
    "created_by_id": "service_89294cac-5a53-4b71-8409-05d0b63203b6",
    "created_by": "service+89294cac-5a53-4b71-8409-05d0b63203b6@no-reply.base44.com",
    "is_sample": false
  },
  {
    "icon_name": "refresh-cw",
    "is_active": true,
    "is_system_defined": true,
    "module_code": "MOD-RENEWAL",
    "module_description": "Renewal workflows, review, approval, and lifecycle tracking",
    "module_name": "Renewal",
    "route_base": "/renewals",
    "sort_order": 50,
    "id": "69c08ed4c743232861cae8dc",
    "created_date": "2026-03-23T00:52:36.923000",
    "updated_date": "2026-03-23T00:52:36.923000",
    "created_by_id": "service_89294cac-5a53-4b71-8409-05d0b63203b6",
    "created_by": "service+89294cac-5a53-4b71-8409-05d0b63203b6@no-reply.base44.com",
    "is_sample": false
  },
  {
    "icon_name": "file-text",
    "is_active": true,
    "is_system_defined": true,
    "module_code": "MOD-CLAIMS",
    "module_description": "Claims processing, review, status, and reporting",
    "module_name": "Claims",
    "route_base": "/claims",
    "sort_order": 40,
    "id": "69c08ed479b1b284ce0e30fa",
    "created_date": "2026-03-23T00:52:36.707000",
    "updated_date": "2026-03-23T00:52:36.707000",
    "created_by_id": "service_89294cac-5a53-4b71-8409-05d0b63203b6",
    "created_by": "service+89294cac-5a53-4b71-8409-05d0b63203b6@no-reply.base44.com",
    "is_sample": false
  },
  {
    "icon_name": "users",
    "is_active": true,
    "is_system_defined": true,
    "module_code": "MOD-EMP",
    "module_description": "Employee and subscriber profile, maintenance, and actions",
    "module_name": "Employee Management",
    "route_base": "/employees",
    "sort_order": 30,
    "id": "69c08ed3c601a0435a0d57ac",
    "created_date": "2026-03-23T00:52:35.910000",
    "updated_date": "2026-03-23T00:52:35.910000",
    "created_by_id": "service_89294cac-5a53-4b71-8409-05d0b63203b6",
    "created_by": "service+89294cac-5a53-4b71-8409-05d0b63203b6@no-reply.base44.com",
    "is_sample": false
  },
  {
    "icon_name": "help-circle",
    "is_active": true,
    "is_system_defined": true,
    "module_code": "MOD-HELP",
    "module_description": "End-user help manual, contextual help, and HelpAI",
    "module_name": "Help Center",
    "route_base": "/help",
    "sort_order": 20,
    "id": "69c08ed36b1d6b942648eb73",
    "created_date": "2026-03-23T00:52:35.695000",
    "updated_date": "2026-03-23T00:52:35.695000",
    "created_by_id": "service_89294cac-5a53-4b71-8409-05d0b63203b6",
    "created_by": "service+89294cac-5a53-4b71-8409-05d0b63203b6@no-reply.base44.com",
    "is_sample": false
  },
  {
    "icon_name": "settings",
    "is_active": true,
    "is_system_defined": true,
    "module_code": "MOD-ADM",
    "module_description": "Administrative tools and governance functions",
    "module_name": "Administration",
    "route_base": "/admin",
    "sort_order": 10,
    "id": "69c08ed364e22777dbad5dec",
    "created_date": "2026-03-23T00:52:35.482000",
    "updated_date": "2026-03-23T00:52:35.482000",
    "created_by_id": "service_89294cac-5a53-4b71-8409-05d0b63203b6",
    "created_by": "service+89294cac-5a53-4b71-8409-05d0b63203b6@no-reply.base44.com",
    "is_sample": false
  }
]